aratree/__init__.py
aratree/metrics.py
aratree/preprocessing.py
aratree/utils.py
aratree/regressors/__init__.py
aratree/regressors/dtr.py
aratree/regressors/rfr.py
aratree-0.1.1.dist-info/METADATA
aratree-0.1.1.dist-info/WHEEL
aratree-0.1.1.dist-info/top_level.txt
aratree-0.1.1.dist-info/RECORD
